CHANGELOG.md
README.md
configuration/__init__.py
configuration/configuration.py
obsidian_utilities/__init__.py
obsidian_utilities/obsidian_utilities.py
templates/__init__.py
templates/copy_template.py
obsidian_utilities-0.0.3.dist-info/METADATA
obsidian_utilities-0.0.3.dist-info/WHEEL
obsidian_utilities-0.0.3.dist-info/entry_points.txt
obsidian_utilities-0.0.3.dist-info/RECORD
